janitor/__init__.py
janitor/biology.py
janitor/chemistry.py
janitor/engineering.py
janitor/errors.py
janitor/finance.py
janitor/io.py
janitor/math.py
janitor/ml.py
janitor/timeseries.py
janitor/utils.py
janitor/accessors/__init__.py
janitor/accessors/data_description.py
janitor/functions/__init__.py
janitor/functions/_numba.py
janitor/functions/add_columns.py
janitor/functions/alias.py
janitor/functions/also.py
janitor/functions/bin_numeric.py
janitor/functions/case_when.py
janitor/functions/change_index_dtype.py
janitor/functions/change_type.py
janitor/functions/clean_names.py
janitor/functions/coalesce.py
janitor/functions/collapse_levels.py
janitor/functions/complete.py
janitor/functions/concatenate_columns.py
janitor/functions/conditional_join.py
janitor/functions/convert_date.py
janitor/functions/count_cumulative_unique.py
janitor/functions/currency_column_to_numeric.py
janitor/functions/deconcatenate_column.py
janitor/functions/drop_constant_columns.py
janitor/functions/drop_duplicate_columns.py
janitor/functions/dropnotnull.py
janitor/functions/encode_categorical.py
janitor/functions/expand_column.py
janitor/functions/expand_grid.py
janitor/functions/explode_index.py
janitor/functions/factorize_columns.py
janitor/functions/fill.py
janitor/functions/filter.py
janitor/functions/find_replace.py
janitor/functions/flag_nulls.py
janitor/functions/get_dupes.py
janitor/functions/groupby_agg.py
janitor/functions/groupby_topk.py
janitor/functions/impute.py
janitor/functions/jitter.py
janitor/functions/join_apply.py
janitor/functions/label_encode.py
janitor/functions/limit_column_characters.py
janitor/functions/min_max_scale.py
janitor/functions/move.py
janitor/functions/mutate.py
janitor/functions/pivot.py
janitor/functions/process_text.py
janitor/functions/remove_columns.py
janitor/functions/remove_empty.py
janitor/functions/rename_columns.py
janitor/functions/reorder_columns.py
janitor/functions/round_to_fraction.py
janitor/functions/row_to_names.py
pyjanitor-0.32.6.dist-info/licenses/LICENSE
pyjanitor-0.32.6.dist-info/METADATA
pyjanitor-0.32.6.dist-info/WHEEL
pyjanitor-0.32.6.dist-info/top_level.txt
pyjanitor-0.32.6.dist-info/RECORD
