Metadata-Version: 2.4
Name: pyjanitor
Version: 0.32.6
Summary: Tools for cleaning pandas DataFrames
Author-email: pyjanitor devs <ericmajinglong@gmail.com>
Maintainer-email: pyjanitor devs <ericmajinglong@gmail.com>
License: MIT
Project-URL: Homepage, https://github.com/pyjanitor-devs/pyjanitor
Project-URL: Documentation, https://pyjanitor-devs.github.io/pyjanitor
Project-URL: Repository, https://github.com/pyjanitor-devs/pyjanitor
Project-URL: Bug Tracker, https://github.com/pyjanitor-devs/pyjanitor/issues
Keywords: pandas,data-cleaning,data-science,janitor
Classifier: Development Status :: 4 - Beta
Classifier: Intended Audience :: Developers
Classifier: Intended Audience :: Science/Research
Classifier: License :: OSI Approved :: MIT License
Classifier: Programming Language :: Python :: 3
Classifier: Programming Language :: Python :: 3.6
Classifier: Programming Language :: Python :: 3.7
Classifier: Programming Language :: Python :: 3.8
Classifier: Programming Language :: Python :: 3.9
Classifier: Programming Language :: Python :: 3.10
Classifier: Programming Language :: Python :: 3.11
Classifier: Topic :: Scientific/Engineering
Requires-Python: >=3.6
License-File: LICENSE
Requires-Dist: natsort
Requires-Dist: pandas-flavor==0.8.1
Requires-Dist: multipledispatch
Requires-Dist: scipy
Requires-Dist: janitor-rs<0.4,>=0.3.0
Provides-Extra: dev
Requires-Dist: pip-tools; extra == "dev"
Requires-Dist: pre-commit; extra == "dev"
Requires-Dist: isort>=4.3.18; extra == "dev"
Requires-Dist: black>=19.3b0; extra == "dev"
Requires-Dist: darglint; extra == "dev"
Requires-Dist: flake8; extra == "dev"
Provides-Extra: docs
Requires-Dist: mkdocs; extra == "docs"
Requires-Dist: polars; extra == "docs"
Requires-Dist: mkdocs-material; extra == "docs"
Requires-Dist: mkdocstrings>=0.19.0; extra == "docs"
Requires-Dist: mkdocstrings-python; extra == "docs"
Requires-Dist: ipython>7.31.1; extra == "docs"
Requires-Dist: biopython; extra == "docs"
Requires-Dist: tqdm; extra == "docs"
Requires-Dist: unyt; extra == "docs"
Requires-Dist: pyspark; extra == "docs"
Provides-Extra: test
Requires-Dist: pytest-cov; extra == "test"
Requires-Dist: pytest-xdist; extra == "test"
Requires-Dist: pytest>=3.4.2; extra == "test"
Requires-Dist: hypothesis>=4.4.0; extra == "test"
Requires-Dist: interrogate; extra == "test"
Requires-Dist: pandas-vet; extra == "test"
Requires-Dist: polars; extra == "test"
Requires-Dist: py>=1.10.0; extra == "test"
Provides-Extra: biology
Requires-Dist: biopython; extra == "biology"
Provides-Extra: chemistry
Requires-Dist: tqdm; extra == "chemistry"
Provides-Extra: engineering
Requires-Dist: unyt; extra == "engineering"
Provides-Extra: spark
Requires-Dist: pyspark; extra == "spark"
Provides-Extra: all
Requires-Dist: pip-tools; extra == "all"
Requires-Dist: pre-commit; extra == "all"
Requires-Dist: isort>=4.3.18; extra == "all"
Requires-Dist: black>=19.3b0; extra == "all"
Requires-Dist: darglint; extra == "all"
Requires-Dist: flake8; extra == "all"
Requires-Dist: mkdocs; extra == "all"
Requires-Dist: polars; extra == "all"
Requires-Dist: mkdocs-material; extra == "all"
Requires-Dist: mkdocstrings>=0.19.0; extra == "all"
Requires-Dist: mkdocstrings-python; extra == "all"
Requires-Dist: ipython>7.31.1; extra == "all"
Requires-Dist: biopython; extra == "all"
Requires-Dist: tqdm; extra == "all"
Requires-Dist: unyt; extra == "all"
Requires-Dist: pyspark; extra == "all"
Requires-Dist: pytest-cov; extra == "all"
Requires-Dist: pytest-xdist; extra == "all"
Requires-Dist: pytest>=3.4.2; extra == "all"
Requires-Dist: hypothesis>=4.4.0; extra == "all"
Requires-Dist: interrogate; extra == "all"
Requires-Dist: pandas-vet; extra == "all"
Requires-Dist: py>=1.10.0; extra == "all"
Dynamic: license-file
